atlas_algo_trading/MT5.py
atlas_algo_trading/__init__.py
atlas_algo_trading-1.0.6.dist-info/licenses/LICENSE
atlas_algo_trading-1.0.6.dist-info/METADATA
atlas_algo_trading-1.0.6.dist-info/WHEEL
atlas_algo_trading-1.0.6.dist-info/top_level.txt
atlas_algo_trading-1.0.6.dist-info/RECORD
