Metadata-Version: 2.4
Name: atlas_algo_trading
Version: 1.0.6
Summary: This module use the Metatatrader5 library to connect with the platform, the functions were adapted to make it easier
Home-page: https://github.com/Moises898/AtlasAlgoTrading
Author: Moises Nava
Author-email: navam9897@gmail.com
Classifier: Programming Language :: Python :: 3
Classifier: License :: OSI Approved :: MIT License
Requires-Python: >=3.9
License-File: LICENSE
Requires-Dist: MetaTrader5==5.0.4424
Requires-Dist: mplfinance==0.12.9b1
Requires-Dist: numpy==1.24.2
Requires-Dist: pandas==2.2.3
Dynamic: author
Dynamic: author-email
Dynamic: classifier
Dynamic: description
Dynamic: description-content-type
Dynamic: home-page
Dynamic: license-file
Dynamic: requires-dist
Dynamic: requires-python
Dynamic: summary
